<?xml version="1.0" encoding="UTF-8"?>
<MetaDataObject xmlns="http://v8.1c.ru/8.3/MDClasses" xmlns:app="http://v8.1c.ru/8.2/managed-application/core" xmlns:cfg="http://v8.1c.ru/8.1/data/enterprise/current-config" xmlns:cmi="http://v8.1c.ru/8.2/managed-application/cmi" xmlns:ent="http://v8.1c.ru/8.1/data/enterprise" xmlns:lf="http://v8.1c.ru/8.2/managed-application/logform" xmlns:style="http://v8.1c.ru/8.1/data/ui/style" xmlns:sys="http://v8.1c.ru/8.1/data/ui/fonts/system" xmlns:v8="http://v8.1c.ru/8.1/data/core" xmlns:v8ui="http://v8.1c.ru/8.1/data/ui" xmlns:web="http://v8.1c.ru/8.1/data/ui/colors/web" xmlns:win="http://v8.1c.ru/8.1/data/ui/colors/windows" xmlns:xen="http://v8.1c.ru/8.3/xcf/enums" xmlns:xpr="http://v8.1c.ru/8.3/xcf/predef" xmlns:xr="http://v8.1c.ru/8.3/xcf/readable" xmlns:xs="http://www.w3.org/2001/XMLSchema" xmlns:xsi="http://www.w3.org/2001/XMLSchema-instance" version="2.6">
	<CalculationRegister uuid="78463f99-e381-482f-b0f6-faaef8067dc2">
		<InternalInfo>
			<xr:GeneratedType name="CalculationRegisterRecord.ЕСНДополнительныеНачисления" category="Record">
				<xr:TypeId>3f829e5c-3c78-4c41-93da-290e0e6bf448</xr:TypeId>
				<xr:ValueId>5d3bf961-cbfd-4aa5-8639-f458e2a6052a</xr:ValueId>
			</xr:GeneratedType>
			<xr:GeneratedType name="CalculationRegisterManager.ЕСНДополнительныеНачисления" category="Manager">
				<xr:TypeId>34cfb950-0613-4202-9e0f-7f45252c3cce</xr:TypeId>
				<xr:ValueId>8299dc10-8ddf-494a-ae97-04e644785cf3</xr:ValueId>
			</xr:GeneratedType>
			<xr:GeneratedType name="CalculationRegisterSelection.ЕСНДополнительныеНачисления" category="Selection">
				<xr:TypeId>bb4864a0-aa79-499e-910d-406edf887345</xr:TypeId>
				<xr:ValueId>8e687b2c-3ae7-467f-8d2d-f75d39a66efe</xr:ValueId>
			</xr:GeneratedType>
			<xr:GeneratedType name="CalculationRegisterList.ЕСНДополнительныеНачисления" category="List">
				<xr:TypeId>54d193e9-32e6-442a-b4bc-654570c31b71</xr:TypeId>
				<xr:ValueId>ff0ababa-97ff-4869-9209-fd165b8786c2</xr:ValueId>
			</xr:GeneratedType>
			<xr:GeneratedType name="CalculationRegisterRecordSet.ЕСНДополнительныеНачисления" category="RecordSet">
				<xr:TypeId>2ca6105f-5f94-48f3-9b8f-1eb82c31895a</xr:TypeId>
				<xr:ValueId>5c86390b-05c4-469a-9c3a-51e8bed00742</xr:ValueId>
			</xr:GeneratedType>
			<xr:GeneratedType name="CalculationRegisterRecordKey.ЕСНДополнительныеНачисления" category="RecordKey">
				<xr:TypeId>84b35a50-2658-4298-be88-7ec6f1aef1ad</xr:TypeId>
				<xr:ValueId>b025c418-fb80-409d-b948-3401f426ae88</xr:ValueId>
			</xr:GeneratedType>
			<xr:GeneratedType name="RecalculationsManager.ЕСНДополнительныеНачисления" category="Recalcs">
				<xr:TypeId>0f21263d-d1f4-463a-ae6c-af3e7cd98b12</xr:TypeId>
				<xr:ValueId>81af8fc6-a13c-4f4f-bf39-a51097eeb8f5</xr:ValueId>
			</xr:GeneratedType>
		</InternalInfo>
		<Properties>
			<Name>ЕСНДополнительныеНачисления</Name>
			<Synonym>
				<v8:item>
					<v8:lang>ru</v8:lang>
					<v8:content>Фонды Дополнительные начисления</v8:content>
				</v8:item>
			</Synonym>
			<Comment>(Регл)</Comment>
			<UseStandardCommands>false</UseStandardCommands>
			<DefaultListForm>CalculationRegister.ЕСНДополнительныеНачисления.Form.ФормаСписка</DefaultListForm>
			<AuxiliaryListForm/>
			<Periodicity>Month</Periodicity>
			<ActionPeriod>false</ActionPeriod>
			<BasePeriod>true</BasePeriod>
			<Schedule/>
			<ScheduleValue/>
			<ScheduleDate/>
			<ChartOfCalculationTypes>ChartOfCalculationTypes.ДополнительныеНачисленияОрганизаций</ChartOfCalculationTypes>
			<IncludeHelpInContents>false</IncludeHelpInContents>
			<DataLockControlMode>Automatic</DataLockControlMode>
			<FullTextSearch>DontUse</FullTextSearch>
			<ListPresentation/>
			<ExtendedListPresentation/>
			<Explanation/>
		</Properties>
		<ChildObjects>
			<Resource uuid="341ee851-6294-47c4-ba3a-256decea483a">
				<Properties>
					<Name>Результат</Name>
					<Synonym>
						<v8:item>
							<v8:lang>ru</v8:lang>
							<v8:content>Результат</v8:content>
						</v8:item>
					</Synonym>
					<Comment/>
					<Type>
						<v8:Type>xs:decimal</v8:Type>
						<v8:NumberQualifiers>
							<v8:Digits>15</v8:Digits>
							<v8:FractionDigits>2</v8:FractionDigits>
							<v8:AllowedSign>Any</v8:AllowedSign>
						</v8:NumberQualifiers>
					</Type>
					<PasswordMode>false</PasswordMode>
					<Format/>
					<EditFormat/>
					<ToolTip/>
					<MarkNegatives>false</MarkNegatives>
					<Mask/>
					<MultiLine>false</MultiLine>
					<ExtendedEdit>false</ExtendedEdit>
					<MinValue xsi:nil="true"/>
					<MaxValue xsi:nil="true"/>
					<FillChecking>DontCheck</FillChecking>
					<ChoiceFoldersAndItems>Items</ChoiceFoldersAndItems>
					<ChoiceParameterLinks/>
					<ChoiceParameters/>
					<QuickChoice>Auto</QuickChoice>
					<CreateOnInput>Auto</CreateOnInput>
					<ChoiceForm/>
					<LinkByType/>
					<ChoiceHistoryOnInput>Auto</ChoiceHistoryOnInput>
					<FullTextSearch>Use</FullTextSearch>
				</Properties>
			</Resource>
			<Resource uuid="2d12794a-3988-48c9-98f6-4288b877d7f3">
				<Properties>
					<Name>Скидка</Name>
					<Synonym>
						<v8:item>
							<v8:lang>ru</v8:lang>
							<v8:content>Скидка</v8:content>
						</v8:item>
					</Synonym>
					<Comment/>
					<Type>
						<v8:Type>xs:decimal</v8:Type>
						<v8:NumberQualifiers>
							<v8:Digits>10</v8:Digits>
							<v8:FractionDigits>2</v8:FractionDigits>
							<v8:AllowedSign>Any</v8:AllowedSign>
						</v8:NumberQualifiers>
					</Type>
					<PasswordMode>false</PasswordMode>
					<Format/>
					<EditFormat/>
					<ToolTip/>
					<MarkNegatives>false</MarkNegatives>
					<Mask/>
					<MultiLine>false</MultiLine>
					<ExtendedEdit>false</ExtendedEdit>
					<MinValue xsi:nil="true"/>
					<MaxValue xsi:nil="true"/>
					<FillChecking>DontCheck</FillChecking>
					<ChoiceFoldersAndItems>Items</ChoiceFoldersAndItems>
					<ChoiceParameterLinks/>
					<ChoiceParameters/>
					<QuickChoice>Auto</QuickChoice>
					<CreateOnInput>Auto</CreateOnInput>
					<ChoiceForm/>
					<LinkByType/>
					<ChoiceHistoryOnInput>Auto</ChoiceHistoryOnInput>
					<FullTextSearch>Use</FullTextSearch>
				</Properties>
			</Resource>
			<Attribute uuid="f4424fde-6c9e-45ca-843d-533d2899a0c6">
				<Properties>
					<Name>ДоходЕдиныйПлатеж</Name>
					<Synonym>
						<v8:item>
							<v8:lang>ru</v8:lang>
							<v8:content>Доход единый платеж</v8:content>
						</v8:item>
					</Synonym>
					<Comment/>
					<Type>
						<v8:Type>cfg:EnumRef.ДоходыФСС_НС</v8:Type>
					</Type>
					<PasswordMode>false</PasswordMode>
					<Format/>
					<EditFormat/>
					<ToolTip/>
					<MarkNegatives>false</MarkNegatives>
					<Mask/>
					<MultiLine>false</MultiLine>
					<ExtendedEdit>false</ExtendedEdit>
					<MinValue xsi:nil="true"/>
					<MaxValue xsi:nil="true"/>
					<FillChecking>DontCheck</FillChecking>
					<ChoiceFoldersAndItems>Items</ChoiceFoldersAndItems>
					<ChoiceParameterLinks/>
					<ChoiceParameters/>
					<QuickChoice>Auto</QuickChoice>
					<CreateOnInput>Auto</CreateOnInput>
					<ChoiceForm/>
					<LinkByType/>
					<ChoiceHistoryOnInput>Auto</ChoiceHistoryOnInput>
					<ScheduleLink/>
					<Indexing>DontIndex</Indexing>
					<FullTextSearch>Use</FullTextSearch>
				</Properties>
			</Attribute>
			<Attribute uuid="5b6c76a9-495d-4113-8600-0fdad685b5d3">
				<Properties>
					<Name>ОбособленноеПодразделение</Name>
					<Synonym>
						<v8:item>
							<v8:lang>ru</v8:lang>
							<v8:content>Обособленное подразделение</v8:content>
						</v8:item>
					</Synonym>
					<Comment/>
					<Type>
						<v8:Type>cfg:CatalogRef.Организации</v8:Type>
					</Type>
					<PasswordMode>false</PasswordMode>
					<Format/>
					<EditFormat/>
					<ToolTip/>
					<MarkNegatives>false</MarkNegatives>
					<Mask/>
					<MultiLine>false</MultiLine>
					<ExtendedEdit>false</ExtendedEdit>
					<MinValue xsi:nil="true"/>
					<MaxValue xsi:nil="true"/>
					<FillChecking>DontCheck</FillChecking>
					<ChoiceFoldersAndItems>Items</ChoiceFoldersAndItems>
					<ChoiceParameterLinks/>
					<ChoiceParameters/>
					<QuickChoice>Auto</QuickChoice>
					<CreateOnInput>Auto</CreateOnInput>
					<ChoiceForm/>
					<LinkByType/>
					<ChoiceHistoryOnInput>Auto</ChoiceHistoryOnInput>
					<ScheduleLink/>
					<Indexing>DontIndex</Indexing>
					<FullTextSearch>Use</FullTextSearch>
				</Properties>
			</Attribute>
			<Attribute uuid="5b738e71-91e9-4955-ad4b-02399c03d01a">
				<Properties>
					<Name>КодДоходаЕСН</Name>
					<Synonym>
						<v8:item>
							<v8:lang>ru</v8:lang>
							<v8:content>Код дохода ЕСН</v8:content>
						</v8:item>
					</Synonym>
					<Comment/>
					<Type>
						<v8:Type>cfg:CatalogRef.ДоходыЕСН</v8:Type>
					</Type>
					<PasswordMode>false</PasswordMode>
					<Format/>
					<EditFormat/>
					<ToolTip/>
					<MarkNegatives>false</MarkNegatives>
					<Mask/>
					<MultiLine>false</MultiLine>
					<ExtendedEdit>false</ExtendedEdit>
					<MinValue xsi:nil="true"/>
					<MaxValue xsi:nil="true"/>
					<FillChecking>DontCheck</FillChecking>
					<ChoiceFoldersAndItems>Items</ChoiceFoldersAndItems>
					<ChoiceParameterLinks/>
					<ChoiceParameters/>
					<QuickChoice>Auto</QuickChoice>
					<CreateOnInput>Auto</CreateOnInput>
					<ChoiceForm/>
					<LinkByType/>
					<ChoiceHistoryOnInput>Auto</ChoiceHistoryOnInput>
					<ScheduleLink/>
					<Indexing>DontIndex</Indexing>
					<FullTextSearch>Use</FullTextSearch>
				</Properties>
			</Attribute>
			<Attribute uuid="fbf659d8-4bab-46ff-bc2d-5463e3343a84">
				<Properties>
					<Name>ДоходФСЗН</Name>
					<Synonym>
						<v8:item>
							<v8:lang>ru</v8:lang>
							<v8:content>Доход ФСЗН (удалить)</v8:content>
						</v8:item>
					</Synonym>
					<Comment/>
					<Type>
						<v8:Type>cfg:EnumRef.ДоходыФСС_НС</v8:Type>
					</Type>
					<PasswordMode>false</PasswordMode>
					<Format/>
					<EditFormat/>
					<ToolTip/>
					<MarkNegatives>false</MarkNegatives>
					<Mask/>
					<MultiLine>false</MultiLine>
					<ExtendedEdit>false</ExtendedEdit>
					<MinValue xsi:nil="true"/>
					<MaxValue xsi:nil="true"/>
					<FillChecking>DontCheck</FillChecking>
					<ChoiceFoldersAndItems>Items</ChoiceFoldersAndItems>
					<ChoiceParameterLinks/>
					<ChoiceParameters/>
					<QuickChoice>Auto</QuickChoice>
					<CreateOnInput>Auto</CreateOnInput>
					<ChoiceForm/>
					<LinkByType/>
					<ChoiceHistoryOnInput>Auto</ChoiceHistoryOnInput>
					<ScheduleLink/>
					<Indexing>DontIndex</Indexing>
					<FullTextSearch>Use</FullTextSearch>
				</Properties>
			</Attribute>
			<Attribute uuid="a7b266ba-6166-4d82-b53a-a55b5c185991">
				<Properties>
					<Name>ДоходСтрах</Name>
					<Synonym>
						<v8:item>
							<v8:lang>ru</v8:lang>
							<v8:content>Доход обязательное страхование (удалить)</v8:content>
						</v8:item>
					</Synonym>
					<Comment/>
					<Type>
						<v8:Type>cfg:EnumRef.ДоходыФСС_НС</v8:Type>
					</Type>
					<PasswordMode>false</PasswordMode>
					<Format/>
					<EditFormat/>
					<ToolTip/>
					<MarkNegatives>false</MarkNegatives>
					<Mask/>
					<MultiLine>false</MultiLine>
					<ExtendedEdit>false</ExtendedEdit>
					<MinValue xsi:nil="true"/>
					<MaxValue xsi:nil="true"/>
					<FillChecking>DontCheck</FillChecking>
					<ChoiceFoldersAndItems>Items</ChoiceFoldersAndItems>
					<ChoiceParameterLinks/>
					<ChoiceParameters/>
					<QuickChoice>Auto</QuickChoice>
					<CreateOnInput>Auto</CreateOnInput>
					<ChoiceForm/>
					<LinkByType/>
					<ChoiceHistoryOnInput>Auto</ChoiceHistoryOnInput>
					<ScheduleLink/>
					<Indexing>DontIndex</Indexing>
					<FullTextSearch>Use</FullTextSearch>
				</Properties>
			</Attribute>
			<Attribute uuid="1a928bb6-83c0-4c51-86b4-88780023c3b5">
				<Properties>
					<Name>ДоходППС</Name>
					<Synonym>
						<v8:item>
							<v8:lang>ru</v8:lang>
							<v8:content>Доход ППС</v8:content>
						</v8:item>
					</Synonym>
					<Comment/>
					<Type>
						<v8:Type>cfg:EnumRef.ДоходыФСС_НС</v8:Type>
					</Type>
					<PasswordMode>false</PasswordMode>
					<Format/>
					<EditFormat/>
					<ToolTip/>
					<MarkNegatives>false</MarkNegatives>
					<Mask/>
					<MultiLine>false</MultiLine>
					<ExtendedEdit>false</ExtendedEdit>
					<MinValue xsi:nil="true"/>
					<MaxValue xsi:nil="true"/>
					<FillChecking>DontCheck</FillChecking>
					<ChoiceFoldersAndItems>Items</ChoiceFoldersAndItems>
					<ChoiceParameterLinks/>
					<ChoiceParameters/>
					<QuickChoice>Auto</QuickChoice>
					<CreateOnInput>Auto</CreateOnInput>
					<ChoiceForm/>
					<LinkByType/>
					<ChoiceHistoryOnInput>Auto</ChoiceHistoryOnInput>
					<ScheduleLink/>
					<Indexing>DontIndex</Indexing>
					<FullTextSearch>Use</FullTextSearch>
				</Properties>
			</Attribute>
			<Attribute uuid="f0420769-e247-48f1-a7b8-f4e3b1a191e9">
				<Properties>
					<Name>ВидДеятельности</Name>
					<Synonym>
						<v8:item>
							<v8:lang>ru</v8:lang>
							<v8:content>Вид деятельности</v8:content>
						</v8:item>
					</Synonym>
					<Comment/>
					<Type>
						<v8:Type>cfg:CatalogRef.ОсобыеУсловияТруда</v8:Type>
					</Type>
					<PasswordMode>false</PasswordMode>
					<Format/>
					<EditFormat/>
					<ToolTip/>
					<MarkNegatives>false</MarkNegatives>
					<Mask/>
					<MultiLine>false</MultiLine>
					<ExtendedEdit>false</ExtendedEdit>
					<MinValue xsi:nil="true"/>
					<MaxValue xsi:nil="true"/>
					<FillChecking>DontCheck</FillChecking>
					<ChoiceFoldersAndItems>Items</ChoiceFoldersAndItems>
					<ChoiceParameterLinks/>
					<ChoiceParameters/>
					<QuickChoice>Auto</QuickChoice>
					<CreateOnInput>Auto</CreateOnInput>
					<ChoiceForm/>
					<LinkByType/>
					<ChoiceHistoryOnInput>Auto</ChoiceHistoryOnInput>
					<ScheduleLink/>
					<Indexing>DontIndex</Indexing>
					<FullTextSearch>Use</FullTextSearch>
				</Properties>
			</Attribute>
			<Attribute uuid="7d16dbcc-f0b8-48e5-a298-43480a3fde43">
				<Properties>
					<Name>БазаФСЗН</Name>
					<Synonym>
						<v8:item>
							<v8:lang>ru</v8:lang>
							<v8:content>База ФСЗН</v8:content>
						</v8:item>
					</Synonym>
					<Comment/>
					<Type>
						<v8:Type>xs:decimal</v8:Type>
						<v8:NumberQualifiers>
							<v8:Digits>15</v8:Digits>
							<v8:FractionDigits>5</v8:FractionDigits>
							<v8:AllowedSign>Any</v8:AllowedSign>
						</v8:NumberQualifiers>
					</Type>
					<PasswordMode>false</PasswordMode>
					<Format/>
					<EditFormat/>
					<ToolTip/>
					<MarkNegatives>false</MarkNegatives>
					<Mask/>
					<MultiLine>false</MultiLine>
					<ExtendedEdit>false</ExtendedEdit>
					<MinValue xsi:nil="true"/>
					<MaxValue xsi:nil="true"/>
					<FillChecking>DontCheck</FillChecking>
					<ChoiceFoldersAndItems>Items</ChoiceFoldersAndItems>
					<ChoiceParameterLinks/>
					<ChoiceParameters/>
					<QuickChoice>Auto</QuickChoice>
					<CreateOnInput>Auto</CreateOnInput>
					<ChoiceForm/>
					<LinkByType/>
					<ChoiceHistoryOnInput>Auto</ChoiceHistoryOnInput>
					<ScheduleLink/>
					<Indexing>DontIndex</Indexing>
					<FullTextSearch>Use</FullTextSearch>
				</Properties>
			</Attribute>
			<Attribute uuid="be178042-30ea-4397-bc33-8046cf3bb1eb">
				<Properties>
					<Name>БазаППС</Name>
					<Synonym>
						<v8:item>
							<v8:lang>ru</v8:lang>
							<v8:content>База ППС</v8:content>
						</v8:item>
					</Synonym>
					<Comment/>
					<Type>
						<v8:Type>xs:decimal</v8:Type>
						<v8:NumberQualifiers>
							<v8:Digits>15</v8:Digits>
							<v8:FractionDigits>5</v8:FractionDigits>
							<v8:AllowedSign>Any</v8:AllowedSign>
						</v8:NumberQualifiers>
					</Type>
					<PasswordMode>false</PasswordMode>
					<Format/>
					<EditFormat/>
					<ToolTip/>
					<MarkNegatives>false</MarkNegatives>
					<Mask/>
					<MultiLine>false</MultiLine>
					<ExtendedEdit>false</ExtendedEdit>
					<MinValue xsi:nil="true"/>
					<MaxValue xsi:nil="true"/>
					<FillChecking>DontCheck</FillChecking>
					<ChoiceFoldersAndItems>Items</ChoiceFoldersAndItems>
					<ChoiceParameterLinks/>
					<ChoiceParameters/>
					<QuickChoice>Auto</QuickChoice>
					<CreateOnInput>Auto</CreateOnInput>
					<ChoiceForm/>
					<LinkByType/>
					<ChoiceHistoryOnInput>Auto</ChoiceHistoryOnInput>
					<ScheduleLink/>
					<Indexing>DontIndex</Indexing>
					<FullTextSearch>Use</FullTextSearch>
				</Properties>
			</Attribute>
			<Attribute uuid="abf2ec33-d9d9-4c8e-b0c1-bac49f332b29">
				<Properties>
					<Name>ДокументОснование</Name>
					<Synonym>
						<v8:item>
							<v8:lang>ru</v8:lang>
							<v8:content>Документ основание</v8:content>
						</v8:item>
					</Synonym>
					<Comment/>
					<Type>
						<v8:Type>cfg:DocumentRef.ДоговорНаВыполнениеРаботСФизЛицом</v8:Type>
					</Type>
					<PasswordMode>false</PasswordMode>
					<Format/>
					<EditFormat/>
					<ToolTip/>
					<MarkNegatives>false</MarkNegatives>
					<Mask/>
					<MultiLine>false</MultiLine>
					<ExtendedEdit>false</ExtendedEdit>
					<MinValue xsi:nil="true"/>
					<MaxValue xsi:nil="true"/>
					<FillChecking>DontCheck</FillChecking>
					<ChoiceFoldersAndItems>Items</ChoiceFoldersAndItems>
					<ChoiceParameterLinks/>
					<ChoiceParameters/>
					<QuickChoice>Auto</QuickChoice>
					<CreateOnInput>Auto</CreateOnInput>
					<ChoiceForm/>
					<LinkByType/>
					<ChoiceHistoryOnInput>Auto</ChoiceHistoryOnInput>
					<ScheduleLink/>
					<Indexing>DontIndex</Indexing>
					<FullTextSearch>Use</FullTextSearch>
				</Properties>
			</Attribute>
			<Attribute uuid="c5d0d980-5479-4fe5-ab3c-d926d1f8620f">
				<Properties>
					<Name>БазаБелгосстрах</Name>
					<Synonym>
						<v8:item>
							<v8:lang>ru</v8:lang>
							<v8:content>База белгосстрах</v8:content>
						</v8:item>
					</Synonym>
					<Comment/>
					<Type>
						<v8:Type>xs:decimal</v8:Type>
						<v8:NumberQualifiers>
							<v8:Digits>15</v8:Digits>
							<v8:FractionDigits>0</v8:FractionDigits>
							<v8:AllowedSign>Any</v8:AllowedSign>
						</v8:NumberQualifiers>
					</Type>
					<PasswordMode>false</PasswordMode>
					<Format/>
					<EditFormat/>
					<ToolTip/>
					<MarkNegatives>false</MarkNegatives>
					<Mask/>
					<MultiLine>false</MultiLine>
					<ExtendedEdit>false</ExtendedEdit>
					<MinValue xsi:nil="true"/>
					<MaxValue xsi:nil="true"/>
					<FillChecking>DontCheck</FillChecking>
					<ChoiceFoldersAndItems>Items</ChoiceFoldersAndItems>
					<ChoiceParameterLinks/>
					<ChoiceParameters/>
					<QuickChoice>Auto</QuickChoice>
					<CreateOnInput>Auto</CreateOnInput>
					<ChoiceForm/>
					<LinkByType/>
					<ChoiceHistoryOnInput>Auto</ChoiceHistoryOnInput>
					<ScheduleLink/>
					<Indexing>DontIndex</Indexing>
					<FullTextSearch>Use</FullTextSearch>
				</Properties>
			</Attribute>
			<Dimension uuid="2f6e0074-6daa-4b42-b782-b77689ea9ddd">
				<Properties>
					<Name>Сотрудник</Name>
					<Synonym>
						<v8:item>
							<v8:lang>ru</v8:lang>
							<v8:content>Сотрудник</v8:content>
						</v8:item>
					</Synonym>
					<Comment/>
					<Type>
						<v8:Type>cfg:CatalogRef.СотрудникиОрганизаций</v8:Type>
					</Type>
					<PasswordMode>false</PasswordMode>
					<Format/>
					<EditFormat/>
					<ToolTip/>
					<MarkNegatives>false</MarkNegatives>
					<Mask/>
					<MultiLine>false</MultiLine>
					<ExtendedEdit>false</ExtendedEdit>
					<MinValue xsi:nil="true"/>
					<MaxValue xsi:nil="true"/>
					<FillChecking>DontCheck</FillChecking>
					<ChoiceFoldersAndItems>Items</ChoiceFoldersAndItems>
					<ChoiceParameterLinks/>
					<ChoiceParameters/>
					<QuickChoice>Auto</QuickChoice>
					<CreateOnInput>Auto</CreateOnInput>
					<ChoiceForm/>
					<LinkByType/>
					<ChoiceHistoryOnInput>Auto</ChoiceHistoryOnInput>
					<DenyIncompleteValues>true</DenyIncompleteValues>
					<BaseDimension>true</BaseDimension>
					<ScheduleLink/>
					<Indexing>DontIndex</Indexing>
					<FullTextSearch>Use</FullTextSearch>
				</Properties>
			</Dimension>
			<Dimension uuid="c2581711-9a64-44b4-ab4e-e6f5602a65ab">
				<Properties>
					<Name>ФизЛицо</Name>
					<Synonym>
						<v8:item>
							<v8:lang>ru</v8:lang>
							<v8:content>Физическое лицо</v8:content>
						</v8:item>
					</Synonym>
					<Comment/>
					<Type>
						<v8:Type>cfg:CatalogRef.ФизическиеЛица</v8:Type>
					</Type>
					<PasswordMode>false</PasswordMode>
					<Format/>
					<EditFormat/>
					<ToolTip/>
					<MarkNegatives>false</MarkNegatives>
					<Mask/>
					<MultiLine>false</MultiLine>
					<ExtendedEdit>false</ExtendedEdit>
					<MinValue xsi:nil="true"/>
					<MaxValue xsi:nil="true"/>
					<FillChecking>DontCheck</FillChecking>
					<ChoiceFoldersAndItems>Items</ChoiceFoldersAndItems>
					<ChoiceParameterLinks/>
					<ChoiceParameters/>
					<QuickChoice>Auto</QuickChoice>
					<CreateOnInput>Auto</CreateOnInput>
					<ChoiceForm/>
					<LinkByType/>
					<ChoiceHistoryOnInput>Auto</ChoiceHistoryOnInput>
					<DenyIncompleteValues>false</DenyIncompleteValues>
					<BaseDimension>false</BaseDimension>
					<ScheduleLink/>
					<Indexing>DontIndex</Indexing>
					<FullTextSearch>Use</FullTextSearch>
				</Properties>
			</Dimension>
			<Dimension uuid="700cf8cd-c296-4860-88b3-464ff6329b76">
				<Properties>
					<Name>Организация</Name>
					<Synonym>
						<v8:item>
							<v8:lang>ru</v8:lang>
							<v8:content>Организация</v8:content>
						</v8:item>
					</Synonym>
					<Comment/>
					<Type>
						<v8:Type>cfg:CatalogRef.Организации</v8:Type>
					</Type>
					<PasswordMode>false</PasswordMode>
					<Format/>
					<EditFormat/>
					<ToolTip/>
					<MarkNegatives>false</MarkNegatives>
					<Mask/>
					<MultiLine>false</MultiLine>
					<ExtendedEdit>false</ExtendedEdit>
					<MinValue xsi:nil="true"/>
					<MaxValue xsi:nil="true"/>
					<FillChecking>DontCheck</FillChecking>
					<ChoiceFoldersAndItems>Items</ChoiceFoldersAndItems>
					<ChoiceParameterLinks/>
					<ChoiceParameters/>
					<QuickChoice>Auto</QuickChoice>
					<CreateOnInput>Auto</CreateOnInput>
					<ChoiceForm/>
					<LinkByType/>
					<ChoiceHistoryOnInput>Auto</ChoiceHistoryOnInput>
					<DenyIncompleteValues>true</DenyIncompleteValues>
					<BaseDimension>false</BaseDimension>
					<ScheduleLink/>
					<Indexing>DontIndex</Indexing>
					<FullTextSearch>Use</FullTextSearch>
				</Properties>
			</Dimension>
			<Dimension uuid="2d668960-6579-40c7-9f36-e500042a1531">
				<Properties>
					<Name>УдалитьПриказ</Name>
					<Synonym>
						<v8:item>
							<v8:lang>ru</v8:lang>
							<v8:content>Удалить приказ</v8:content>
						</v8:item>
					</Synonym>
					<Comment/>
					<Type>
						<v8:Type>cfg:DocumentRef.ПриемНаРаботуВОрганизацию</v8:Type>
					</Type>
					<PasswordMode>false</PasswordMode>
					<Format/>
					<EditFormat/>
					<ToolTip/>
					<MarkNegatives>false</MarkNegatives>
					<Mask/>
					<MultiLine>false</MultiLine>
					<ExtendedEdit>false</ExtendedEdit>
					<MinValue xsi:nil="true"/>
					<MaxValue xsi:nil="true"/>
					<FillChecking>DontCheck</FillChecking>
					<ChoiceFoldersAndItems>Items</ChoiceFoldersAndItems>
					<ChoiceParameterLinks/>
					<ChoiceParameters/>
					<QuickChoice>Auto</QuickChoice>
					<CreateOnInput>Auto</CreateOnInput>
					<ChoiceForm/>
					<LinkByType/>
					<ChoiceHistoryOnInput>Auto</ChoiceHistoryOnInput>
					<DenyIncompleteValues>false</DenyIncompleteValues>
					<BaseDimension>false</BaseDimension>
					<ScheduleLink/>
					<Indexing>DontIndex</Indexing>
					<FullTextSearch>Use</FullTextSearch>
				</Properties>
			</Dimension>
			<Form>ФормаСписка</Form>
		</ChildObjects>
	</CalculationRegister>
</MetaDataObject>