<?xml version="1.0" encoding="UTF-8"?>
<MetaDataObject xmlns="http://v8.1c.ru/8.3/MDClasses" xmlns:app="http://v8.1c.ru/8.2/managed-application/core" xmlns:cfg="http://v8.1c.ru/8.1/data/enterprise/current-config" xmlns:cmi="http://v8.1c.ru/8.2/managed-application/cmi" xmlns:ent="http://v8.1c.ru/8.1/data/enterprise" xmlns:lf="http://v8.1c.ru/8.2/managed-application/logform" xmlns:style="http://v8.1c.ru/8.1/data/ui/style" xmlns:sys="http://v8.1c.ru/8.1/data/ui/fonts/system" xmlns:v8="http://v8.1c.ru/8.1/data/core" xmlns:v8ui="http://v8.1c.ru/8.1/data/ui" xmlns:web="http://v8.1c.ru/8.1/data/ui/colors/web" xmlns:win="http://v8.1c.ru/8.1/data/ui/colors/windows" xmlns:xen="http://v8.1c.ru/8.3/xcf/enums" xmlns:xpr="http://v8.1c.ru/8.3/xcf/predef" xmlns:xr="http://v8.1c.ru/8.3/xcf/readable" xmlns:xs="http://www.w3.org/2001/XMLSchema" xmlns:xsi="http://www.w3.org/2001/XMLSchema-instance" version="2.6">
	<CalculationRegister uuid="96368e87-70db-4857-b75e-039fbb59e5a7">
		<InternalInfo>
			<xr:GeneratedType name="CalculationRegisterRecord.ЕСНОсновныеНачисления" category="Record">
				<xr:TypeId>f08a0eeb-7e0b-4722-a06d-65234017f915</xr:TypeId>
				<xr:ValueId>613ee526-03da-4cc4-8c55-8bdd108a7d3a</xr:ValueId>
			</xr:GeneratedType>
			<xr:GeneratedType name="CalculationRegisterManager.ЕСНОсновныеНачисления" category="Manager">
				<xr:TypeId>bf848ade-c6ae-4767-9592-ac7c7a684952</xr:TypeId>
				<xr:ValueId>8de57c85-4152-4e43-9530-894e320ee5be</xr:ValueId>
			</xr:GeneratedType>
			<xr:GeneratedType name="CalculationRegisterSelection.ЕСНОсновныеНачисления" category="Selection">
				<xr:TypeId>c146b865-22d2-468e-8895-74c0ff3d4cbe</xr:TypeId>
				<xr:ValueId>fdfe70f5-def8-4482-9c2f-b302b3d76cfb</xr:ValueId>
			</xr:GeneratedType>
			<xr:GeneratedType name="CalculationRegisterList.ЕСНОсновныеНачисления" category="List">
				<xr:TypeId>82808cf4-aa93-46ba-bb1c-cc15b399caaa</xr:TypeId>
				<xr:ValueId>bd69348b-3970-4aae-a39d-49c50758a75d</xr:ValueId>
			</xr:GeneratedType>
			<xr:GeneratedType name="CalculationRegisterRecordSet.ЕСНОсновныеНачисления" category="RecordSet">
				<xr:TypeId>97a2ce8d-5a90-4062-aeb6-ae28be701b3f</xr:TypeId>
				<xr:ValueId>4ff4faa0-045c-471c-b247-88b0505d1fb0</xr:ValueId>
			</xr:GeneratedType>
			<xr:GeneratedType name="CalculationRegisterRecordKey.ЕСНОсновныеНачисления" category="RecordKey">
				<xr:TypeId>66c29cde-e543-4b9d-a868-88209d32e192</xr:TypeId>
				<xr:ValueId>9d07c6fe-9ebf-46b6-9f5e-60911c58288d</xr:ValueId>
			</xr:GeneratedType>
			<xr:GeneratedType name="RecalculationsManager.ЕСНОсновныеНачисления" category="Recalcs">
				<xr:TypeId>666b37f0-4efc-4244-a4ea-e524d719b354</xr:TypeId>
				<xr:ValueId>f5188bb5-612f-453d-8973-88c77187dc62</xr:ValueId>
			</xr:GeneratedType>
		</InternalInfo>
		<Properties>
			<Name>ЕСНОсновныеНачисления</Name>
			<Synonym>
				<v8:item>
					<v8:lang>ru</v8:lang>
					<v8:content>Фонды Основные начисления</v8:content>
				</v8:item>
			</Synonym>
			<Comment>(Регл)</Comment>
			<UseStandardCommands>false</UseStandardCommands>
			<DefaultListForm>CalculationRegister.ЕСНОсновныеНачисления.Form.ФормаСписка</DefaultListForm>
			<AuxiliaryListForm/>
			<Periodicity>Month</Periodicity>
			<ActionPeriod>true</ActionPeriod>
			<BasePeriod>false</BasePeriod>
			<Schedule>InformationRegister.ГрафикиРаботыПоВидамВремени</Schedule>
			<ScheduleValue>InformationRegister.ГрафикиРаботыПоВидамВремени.Resource.ОсновноеЗначение</ScheduleValue>
			<ScheduleDate>InformationRegister.ГрафикиРаботыПоВидамВремени.Dimension.Дата</ScheduleDate>
			<ChartOfCalculationTypes>ChartOfCalculationTypes.ОсновныеНачисленияОрганизаций</ChartOfCalculationTypes>
			<IncludeHelpInContents>false</IncludeHelpInContents>
			<DataLockControlMode>Automatic</DataLockControlMode>
			<FullTextSearch>DontUse</FullTextSearch>
			<ListPresentation/>
			<ExtendedListPresentation/>
			<Explanation/>
		</Properties>
		<ChildObjects>
			<Resource uuid="798dbbf3-ce37-4ac8-82d7-21061a77d682">
				<Properties>
					<Name>Результат</Name>
					<Synonym>
						<v8:item>
							<v8:lang>ru</v8:lang>
							<v8:content>Результат</v8:content>
						</v8:item>
					</Synonym>
					<Comment/>
					<Type>
						<v8:Type>xs:decimal</v8:Type>
						<v8:NumberQualifiers>
							<v8:Digits>15</v8:Digits>
							<v8:FractionDigits>2</v8:FractionDigits>
							<v8:AllowedSign>Any</v8:AllowedSign>
						</v8:NumberQualifiers>
					</Type>
					<PasswordMode>false</PasswordMode>
					<Format/>
					<EditFormat/>
					<ToolTip/>
					<MarkNegatives>false</MarkNegatives>
					<Mask/>
					<MultiLine>false</MultiLine>
					<ExtendedEdit>false</ExtendedEdit>
					<MinValue xsi:nil="true"/>
					<MaxValue xsi:nil="true"/>
					<FillChecking>DontCheck</FillChecking>
					<ChoiceFoldersAndItems>Items</ChoiceFoldersAndItems>
					<ChoiceParameterLinks/>
					<ChoiceParameters/>
					<QuickChoice>Auto</QuickChoice>
					<CreateOnInput>Auto</CreateOnInput>
					<ChoiceForm/>
					<LinkByType/>
					<ChoiceHistoryOnInput>Auto</ChoiceHistoryOnInput>
					<FullTextSearch>Use</FullTextSearch>
				</Properties>
			</Resource>
			<Attribute uuid="bc622086-aac0-4fe2-b03d-93c665a61c7f">
				<Properties>
					<Name>ГрафикРаботы</Name>
					<Synonym>
						<v8:item>
							<v8:lang>ru</v8:lang>
							<v8:content>График работы</v8:content>
						</v8:item>
					</Synonym>
					<Comment/>
					<Type>
						<v8:Type>cfg:CatalogRef.ГрафикиРаботы</v8:Type>
					</Type>
					<PasswordMode>false</PasswordMode>
					<Format/>
					<EditFormat/>
					<ToolTip/>
					<MarkNegatives>false</MarkNegatives>
					<Mask/>
					<MultiLine>false</MultiLine>
					<ExtendedEdit>false</ExtendedEdit>
					<MinValue xsi:nil="true"/>
					<MaxValue xsi:nil="true"/>
					<FillChecking>DontCheck</FillChecking>
					<ChoiceFoldersAndItems>Items</ChoiceFoldersAndItems>
					<ChoiceParameterLinks/>
					<ChoiceParameters/>
					<QuickChoice>Auto</QuickChoice>
					<CreateOnInput>Auto</CreateOnInput>
					<ChoiceForm/>
					<LinkByType/>
					<ChoiceHistoryOnInput>Auto</ChoiceHistoryOnInput>
					<ScheduleLink>InformationRegister.ГрафикиРаботыПоВидамВремени.Dimension.ГрафикРаботы</ScheduleLink>
					<Indexing>DontIndex</Indexing>
					<FullTextSearch>Use</FullTextSearch>
				</Properties>
			</Attribute>
			<Attribute uuid="cc8fac1f-36f3-4d1b-8a5d-e966f45d6c31">
				<Properties>
					<Name>ВидУчетаВремени</Name>
					<Synonym>
						<v8:item>
							<v8:lang>ru</v8:lang>
							<v8:content>Вид учета времени</v8:content>
						</v8:item>
					</Synonym>
					<Comment/>
					<Type>
						<v8:Type>cfg:EnumRef.ВидыУчетаВремени</v8:Type>
					</Type>
					<PasswordMode>false</PasswordMode>
					<Format/>
					<EditFormat/>
					<ToolTip/>
					<MarkNegatives>false</MarkNegatives>
					<Mask/>
					<MultiLine>false</MultiLine>
					<ExtendedEdit>false</ExtendedEdit>
					<MinValue xsi:nil="true"/>
					<MaxValue xsi:nil="true"/>
					<FillChecking>DontCheck</FillChecking>
					<ChoiceFoldersAndItems>Items</ChoiceFoldersAndItems>
					<ChoiceParameterLinks/>
					<ChoiceParameters/>
					<QuickChoice>Auto</QuickChoice>
					<CreateOnInput>Auto</CreateOnInput>
					<ChoiceForm/>
					<LinkByType/>
					<ChoiceHistoryOnInput>Auto</ChoiceHistoryOnInput>
					<ScheduleLink>InformationRegister.ГрафикиРаботыПоВидамВремени.Dimension.ВидУчетаВремени</ScheduleLink>
					<Indexing>DontIndex</Indexing>
					<FullTextSearch>Use</FullTextSearch>
				</Properties>
			</Attribute>
			<Attribute uuid="cb729319-fa6a-4235-ab33-5892939c01ef">
				<Properties>
					<Name>ДоходЕдиныйПлатеж</Name>
					<Synonym>
						<v8:item>
							<v8:lang>ru</v8:lang>
							<v8:content>Доход единый платеж</v8:content>
						</v8:item>
					</Synonym>
					<Comment/>
					<Type>
						<v8:Type>cfg:EnumRef.ДоходыФСС_НС</v8:Type>
					</Type>
					<PasswordMode>false</PasswordMode>
					<Format/>
					<EditFormat/>
					<ToolTip/>
					<MarkNegatives>false</MarkNegatives>
					<Mask/>
					<MultiLine>false</MultiLine>
					<ExtendedEdit>false</ExtendedEdit>
					<MinValue xsi:nil="true"/>
					<MaxValue xsi:nil="true"/>
					<FillChecking>DontCheck</FillChecking>
					<ChoiceFoldersAndItems>Items</ChoiceFoldersAndItems>
					<ChoiceParameterLinks/>
					<ChoiceParameters/>
					<QuickChoice>Auto</QuickChoice>
					<CreateOnInput>Auto</CreateOnInput>
					<ChoiceForm/>
					<LinkByType/>
					<ChoiceHistoryOnInput>Auto</ChoiceHistoryOnInput>
					<ScheduleLink/>
					<Indexing>DontIndex</Indexing>
					<FullTextSearch>Use</FullTextSearch>
				</Properties>
			</Attribute>
			<Attribute uuid="05c24a74-be9e-4e15-bb9b-b17b1b81ec7d">
				<Properties>
					<Name>ОбособленноеПодразделение</Name>
					<Synonym>
						<v8:item>
							<v8:lang>ru</v8:lang>
							<v8:content>Обособленное подразделение</v8:content>
						</v8:item>
					</Synonym>
					<Comment/>
					<Type>
						<v8:Type>cfg:CatalogRef.Организации</v8:Type>
					</Type>
					<PasswordMode>false</PasswordMode>
					<Format/>
					<EditFormat/>
					<ToolTip/>
					<MarkNegatives>false</MarkNegatives>
					<Mask/>
					<MultiLine>false</MultiLine>
					<ExtendedEdit>false</ExtendedEdit>
					<MinValue xsi:nil="true"/>
					<MaxValue xsi:nil="true"/>
					<FillChecking>DontCheck</FillChecking>
					<ChoiceFoldersAndItems>Items</ChoiceFoldersAndItems>
					<ChoiceParameterLinks/>
					<ChoiceParameters/>
					<QuickChoice>Auto</QuickChoice>
					<CreateOnInput>Auto</CreateOnInput>
					<ChoiceForm/>
					<LinkByType/>
					<ChoiceHistoryOnInput>Auto</ChoiceHistoryOnInput>
					<ScheduleLink/>
					<Indexing>DontIndex</Indexing>
					<FullTextSearch>Use</FullTextSearch>
				</Properties>
			</Attribute>
			<Attribute uuid="68826e7e-8952-41f0-a79a-770486a7ca6f">
				<Properties>
					<Name>КодДоходаЕСН</Name>
					<Synonym>
						<v8:item>
							<v8:lang>ru</v8:lang>
							<v8:content>Код дохода ЕСН</v8:content>
						</v8:item>
					</Synonym>
					<Comment/>
					<Type>
						<v8:Type>cfg:CatalogRef.ДоходыЕСН</v8:Type>
					</Type>
					<PasswordMode>false</PasswordMode>
					<Format/>
					<EditFormat/>
					<ToolTip/>
					<MarkNegatives>false</MarkNegatives>
					<Mask/>
					<MultiLine>false</MultiLine>
					<ExtendedEdit>false</ExtendedEdit>
					<MinValue xsi:nil="true"/>
					<MaxValue xsi:nil="true"/>
					<FillChecking>DontCheck</FillChecking>
					<ChoiceFoldersAndItems>Items</ChoiceFoldersAndItems>
					<ChoiceParameterLinks/>
					<ChoiceParameters/>
					<QuickChoice>Auto</QuickChoice>
					<CreateOnInput>Auto</CreateOnInput>
					<ChoiceForm/>
					<LinkByType/>
					<ChoiceHistoryOnInput>Auto</ChoiceHistoryOnInput>
					<ScheduleLink/>
					<Indexing>DontIndex</Indexing>
					<FullTextSearch>Use</FullTextSearch>
				</Properties>
			</Attribute>
			<Attribute uuid="16f732bd-80e0-4f8c-80bc-b915df3c15e9">
				<Properties>
					<Name>ДоходФСЗН</Name>
					<Synonym>
						<v8:item>
							<v8:lang>ru</v8:lang>
							<v8:content>Доход ФСЗН</v8:content>
						</v8:item>
					</Synonym>
					<Comment/>
					<Type>
						<v8:Type>cfg:EnumRef.ДоходыФСС_НС</v8:Type>
					</Type>
					<PasswordMode>false</PasswordMode>
					<Format/>
					<EditFormat/>
					<ToolTip/>
					<MarkNegatives>false</MarkNegatives>
					<Mask/>
					<MultiLine>false</MultiLine>
					<ExtendedEdit>false</ExtendedEdit>
					<MinValue xsi:nil="true"/>
					<MaxValue xsi:nil="true"/>
					<FillChecking>DontCheck</FillChecking>
					<ChoiceFoldersAndItems>Items</ChoiceFoldersAndItems>
					<ChoiceParameterLinks/>
					<ChoiceParameters/>
					<QuickChoice>Auto</QuickChoice>
					<CreateOnInput>Auto</CreateOnInput>
					<ChoiceForm/>
					<LinkByType/>
					<ChoiceHistoryOnInput>Auto</ChoiceHistoryOnInput>
					<ScheduleLink/>
					<Indexing>DontIndex</Indexing>
					<FullTextSearch>Use</FullTextSearch>
				</Properties>
			</Attribute>
			<Attribute uuid="8cdedf74-a261-4297-b123-ef83c33ead7d">
				<Properties>
					<Name>ДоходСтрах</Name>
					<Synonym>
						<v8:item>
							<v8:lang>ru</v8:lang>
							<v8:content>Доход обязательное страхование</v8:content>
						</v8:item>
					</Synonym>
					<Comment/>
					<Type>
						<v8:Type>cfg:EnumRef.ДоходыФСС_НС</v8:Type>
					</Type>
					<PasswordMode>false</PasswordMode>
					<Format/>
					<EditFormat/>
					<ToolTip/>
					<MarkNegatives>false</MarkNegatives>
					<Mask/>
					<MultiLine>false</MultiLine>
					<ExtendedEdit>false</ExtendedEdit>
					<MinValue xsi:nil="true"/>
					<MaxValue xsi:nil="true"/>
					<FillChecking>DontCheck</FillChecking>
					<ChoiceFoldersAndItems>Items</ChoiceFoldersAndItems>
					<ChoiceParameterLinks/>
					<ChoiceParameters/>
					<QuickChoice>Auto</QuickChoice>
					<CreateOnInput>Auto</CreateOnInput>
					<ChoiceForm/>
					<LinkByType/>
					<ChoiceHistoryOnInput>Auto</ChoiceHistoryOnInput>
					<ScheduleLink/>
					<Indexing>DontIndex</Indexing>
					<FullTextSearch>Use</FullTextSearch>
				</Properties>
			</Attribute>
			<Attribute uuid="6a9a9a63-1360-47b6-8f5b-b0cc55831599">
				<Properties>
					<Name>ДоходППС</Name>
					<Synonym>
						<v8:item>
							<v8:lang>ru</v8:lang>
							<v8:content>Доход ППС</v8:content>
						</v8:item>
					</Synonym>
					<Comment/>
					<Type>
						<v8:Type>cfg:EnumRef.ДоходыФСС_НС</v8:Type>
					</Type>
					<PasswordMode>false</PasswordMode>
					<Format/>
					<EditFormat/>
					<ToolTip/>
					<MarkNegatives>false</MarkNegatives>
					<Mask/>
					<MultiLine>false</MultiLine>
					<ExtendedEdit>false</ExtendedEdit>
					<MinValue xsi:nil="true"/>
					<MaxValue xsi:nil="true"/>
					<FillChecking>DontCheck</FillChecking>
					<ChoiceFoldersAndItems>Items</ChoiceFoldersAndItems>
					<ChoiceParameterLinks/>
					<ChoiceParameters/>
					<QuickChoice>Auto</QuickChoice>
					<CreateOnInput>Auto</CreateOnInput>
					<ChoiceForm/>
					<LinkByType/>
					<ChoiceHistoryOnInput>Auto</ChoiceHistoryOnInput>
					<ScheduleLink/>
					<Indexing>DontIndex</Indexing>
					<FullTextSearch>Use</FullTextSearch>
				</Properties>
			</Attribute>
			<Attribute uuid="f2f208f1-a244-4d37-bc59-faff6fee35be">
				<Properties>
					<Name>ВидДеятельности</Name>
					<Synonym>
						<v8:item>
							<v8:lang>ru</v8:lang>
							<v8:content>Вид деятельности</v8:content>
						</v8:item>
					</Synonym>
					<Comment/>
					<Type>
						<v8:Type>cfg:CatalogRef.ОсобыеУсловияТруда</v8:Type>
					</Type>
					<PasswordMode>false</PasswordMode>
					<Format/>
					<EditFormat/>
					<ToolTip/>
					<MarkNegatives>false</MarkNegatives>
					<Mask/>
					<MultiLine>false</MultiLine>
					<ExtendedEdit>false</ExtendedEdit>
					<MinValue xsi:nil="true"/>
					<MaxValue xsi:nil="true"/>
					<FillChecking>DontCheck</FillChecking>
					<ChoiceFoldersAndItems>Items</ChoiceFoldersAndItems>
					<ChoiceParameterLinks/>
					<ChoiceParameters/>
					<QuickChoice>Auto</QuickChoice>
					<CreateOnInput>Auto</CreateOnInput>
					<ChoiceForm/>
					<LinkByType/>
					<ChoiceHistoryOnInput>Auto</ChoiceHistoryOnInput>
					<ScheduleLink/>
					<Indexing>DontIndex</Indexing>
					<FullTextSearch>Use</FullTextSearch>
				</Properties>
			</Attribute>
			<Attribute uuid="7e6095ba-c7de-43fd-adff-707484c011a5">
				<Properties>
					<Name>БазаФСЗН</Name>
					<Synonym>
						<v8:item>
							<v8:lang>ru</v8:lang>
							<v8:content>База ФСЗН</v8:content>
						</v8:item>
					</Synonym>
					<Comment/>
					<Type>
						<v8:Type>xs:decimal</v8:Type>
						<v8:NumberQualifiers>
							<v8:Digits>15</v8:Digits>
							<v8:FractionDigits>5</v8:FractionDigits>
							<v8:AllowedSign>Any</v8:AllowedSign>
						</v8:NumberQualifiers>
					</Type>
					<PasswordMode>false</PasswordMode>
					<Format/>
					<EditFormat/>
					<ToolTip/>
					<MarkNegatives>false</MarkNegatives>
					<Mask/>
					<MultiLine>false</MultiLine>
					<ExtendedEdit>false</ExtendedEdit>
					<MinValue xsi:nil="true"/>
					<MaxValue xsi:nil="true"/>
					<FillChecking>DontCheck</FillChecking>
					<ChoiceFoldersAndItems>Items</ChoiceFoldersAndItems>
					<ChoiceParameterLinks/>
					<ChoiceParameters/>
					<QuickChoice>Auto</QuickChoice>
					<CreateOnInput>Auto</CreateOnInput>
					<ChoiceForm/>
					<LinkByType/>
					<ChoiceHistoryOnInput>Auto</ChoiceHistoryOnInput>
					<ScheduleLink/>
					<Indexing>DontIndex</Indexing>
					<FullTextSearch>Use</FullTextSearch>
				</Properties>
			</Attribute>
			<Attribute uuid="3672a8e5-55cd-417c-a270-5972e05850b2">
				<Properties>
					<Name>БазаППС</Name>
					<Synonym>
						<v8:item>
							<v8:lang>ru</v8:lang>
							<v8:content>База ППС</v8:content>
						</v8:item>
					</Synonym>
					<Comment/>
					<Type>
						<v8:Type>xs:decimal</v8:Type>
						<v8:NumberQualifiers>
							<v8:Digits>15</v8:Digits>
							<v8:FractionDigits>5</v8:FractionDigits>
							<v8:AllowedSign>Any</v8:AllowedSign>
						</v8:NumberQualifiers>
					</Type>
					<PasswordMode>false</PasswordMode>
					<Format/>
					<EditFormat/>
					<ToolTip/>
					<MarkNegatives>false</MarkNegatives>
					<Mask/>
					<MultiLine>false</MultiLine>
					<ExtendedEdit>false</ExtendedEdit>
					<MinValue xsi:nil="true"/>
					<MaxValue xsi:nil="true"/>
					<FillChecking>DontCheck</FillChecking>
					<ChoiceFoldersAndItems>Items</ChoiceFoldersAndItems>
					<ChoiceParameterLinks/>
					<ChoiceParameters/>
					<QuickChoice>Auto</QuickChoice>
					<CreateOnInput>Auto</CreateOnInput>
					<ChoiceForm/>
					<LinkByType/>
					<ChoiceHistoryOnInput>Auto</ChoiceHistoryOnInput>
					<ScheduleLink/>
					<Indexing>DontIndex</Indexing>
					<FullTextSearch>Use</FullTextSearch>
				</Properties>
			</Attribute>
			<Attribute uuid="a884532c-1f4d-46d6-8bae-514ac756b980">
				<Properties>
					<Name>БазаБелгосстрах</Name>
					<Synonym>
						<v8:item>
							<v8:lang>ru</v8:lang>
							<v8:content>База белгосстрах</v8:content>
						</v8:item>
					</Synonym>
					<Comment/>
					<Type>
						<v8:Type>xs:decimal</v8:Type>
						<v8:NumberQualifiers>
							<v8:Digits>15</v8:Digits>
							<v8:FractionDigits>0</v8:FractionDigits>
							<v8:AllowedSign>Any</v8:AllowedSign>
						</v8:NumberQualifiers>
					</Type>
					<PasswordMode>false</PasswordMode>
					<Format/>
					<EditFormat/>
					<ToolTip/>
					<MarkNegatives>false</MarkNegatives>
					<Mask/>
					<MultiLine>false</MultiLine>
					<ExtendedEdit>false</ExtendedEdit>
					<MinValue xsi:nil="true"/>
					<MaxValue xsi:nil="true"/>
					<FillChecking>DontCheck</FillChecking>
					<ChoiceFoldersAndItems>Items</ChoiceFoldersAndItems>
					<ChoiceParameterLinks/>
					<ChoiceParameters/>
					<QuickChoice>Auto</QuickChoice>
					<CreateOnInput>Auto</CreateOnInput>
					<ChoiceForm/>
					<LinkByType/>
					<ChoiceHistoryOnInput>Auto</ChoiceHistoryOnInput>
					<ScheduleLink/>
					<Indexing>DontIndex</Indexing>
					<FullTextSearch>Use</FullTextSearch>
				</Properties>
			</Attribute>
			<Dimension uuid="70bec73d-b8a3-48a5-8f9b-f6e216453cf0">
				<Properties>
					<Name>Сотрудник</Name>
					<Synonym>
						<v8:item>
							<v8:lang>ru</v8:lang>
							<v8:content>Сотрудник</v8:content>
						</v8:item>
					</Synonym>
					<Comment/>
					<Type>
						<v8:Type>cfg:CatalogRef.СотрудникиОрганизаций</v8:Type>
					</Type>
					<PasswordMode>false</PasswordMode>
					<Format/>
					<EditFormat/>
					<ToolTip/>
					<MarkNegatives>false</MarkNegatives>
					<Mask/>
					<MultiLine>false</MultiLine>
					<ExtendedEdit>false</ExtendedEdit>
					<MinValue xsi:nil="true"/>
					<MaxValue xsi:nil="true"/>
					<FillChecking>DontCheck</FillChecking>
					<ChoiceFoldersAndItems>Items</ChoiceFoldersAndItems>
					<ChoiceParameterLinks/>
					<ChoiceParameters/>
					<QuickChoice>Auto</QuickChoice>
					<CreateOnInput>Auto</CreateOnInput>
					<ChoiceForm/>
					<LinkByType/>
					<ChoiceHistoryOnInput>Auto</ChoiceHistoryOnInput>
					<DenyIncompleteValues>true</DenyIncompleteValues>
					<BaseDimension>true</BaseDimension>
					<ScheduleLink/>
					<Indexing>DontIndex</Indexing>
					<FullTextSearch>Use</FullTextSearch>
				</Properties>
			</Dimension>
			<Dimension uuid="046cd3ed-ee67-4ff1-91be-bb19558504aa">
				<Properties>
					<Name>ФизЛицо</Name>
					<Synonym>
						<v8:item>
							<v8:lang>ru</v8:lang>
							<v8:content>Физическое лицо</v8:content>
						</v8:item>
					</Synonym>
					<Comment/>
					<Type>
						<v8:Type>cfg:CatalogRef.ФизическиеЛица</v8:Type>
					</Type>
					<PasswordMode>false</PasswordMode>
					<Format/>
					<EditFormat/>
					<ToolTip/>
					<MarkNegatives>false</MarkNegatives>
					<Mask/>
					<MultiLine>false</MultiLine>
					<ExtendedEdit>false</ExtendedEdit>
					<MinValue xsi:nil="true"/>
					<MaxValue xsi:nil="true"/>
					<FillChecking>DontCheck</FillChecking>
					<ChoiceFoldersAndItems>Items</ChoiceFoldersAndItems>
					<ChoiceParameterLinks/>
					<ChoiceParameters/>
					<QuickChoice>Auto</QuickChoice>
					<CreateOnInput>Auto</CreateOnInput>
					<ChoiceForm/>
					<LinkByType/>
					<ChoiceHistoryOnInput>Auto</ChoiceHistoryOnInput>
					<DenyIncompleteValues>false</DenyIncompleteValues>
					<BaseDimension>false</BaseDimension>
					<ScheduleLink/>
					<Indexing>DontIndex</Indexing>
					<FullTextSearch>Use</FullTextSearch>
				</Properties>
			</Dimension>
			<Dimension uuid="b15f6e47-a1c7-422f-97d1-2f2b4243cdd3">
				<Properties>
					<Name>Организация</Name>
					<Synonym>
						<v8:item>
							<v8:lang>ru</v8:lang>
							<v8:content>Организация</v8:content>
						</v8:item>
					</Synonym>
					<Comment/>
					<Type>
						<v8:Type>cfg:CatalogRef.Организации</v8:Type>
					</Type>
					<PasswordMode>false</PasswordMode>
					<Format/>
					<EditFormat/>
					<ToolTip/>
					<MarkNegatives>false</MarkNegatives>
					<Mask/>
					<MultiLine>false</MultiLine>
					<ExtendedEdit>false</ExtendedEdit>
					<MinValue xsi:nil="true"/>
					<MaxValue xsi:nil="true"/>
					<FillChecking>DontCheck</FillChecking>
					<ChoiceFoldersAndItems>Items</ChoiceFoldersAndItems>
					<ChoiceParameterLinks/>
					<ChoiceParameters/>
					<QuickChoice>Auto</QuickChoice>
					<CreateOnInput>Auto</CreateOnInput>
					<ChoiceForm/>
					<LinkByType/>
					<ChoiceHistoryOnInput>Auto</ChoiceHistoryOnInput>
					<DenyIncompleteValues>false</DenyIncompleteValues>
					<BaseDimension>false</BaseDimension>
					<ScheduleLink/>
					<Indexing>DontIndex</Indexing>
					<FullTextSearch>Use</FullTextSearch>
				</Properties>
			</Dimension>
			<Dimension uuid="81108c66-135c-49f4-acad-6c486057e0bb">
				<Properties>
					<Name>УдалитьПриказ</Name>
					<Synonym>
						<v8:item>
							<v8:lang>ru</v8:lang>
							<v8:content>Удалить приказ</v8:content>
						</v8:item>
					</Synonym>
					<Comment/>
					<Type>
						<v8:Type>cfg:DocumentRef.ПриемНаРаботуВОрганизацию</v8:Type>
					</Type>
					<PasswordMode>false</PasswordMode>
					<Format/>
					<EditFormat/>
					<ToolTip/>
					<MarkNegatives>false</MarkNegatives>
					<Mask/>
					<MultiLine>false</MultiLine>
					<ExtendedEdit>false</ExtendedEdit>
					<MinValue xsi:nil="true"/>
					<MaxValue xsi:nil="true"/>
					<FillChecking>DontCheck</FillChecking>
					<ChoiceFoldersAndItems>Items</ChoiceFoldersAndItems>
					<ChoiceParameterLinks/>
					<ChoiceParameters/>
					<QuickChoice>Auto</QuickChoice>
					<CreateOnInput>Auto</CreateOnInput>
					<ChoiceForm/>
					<LinkByType/>
					<ChoiceHistoryOnInput>Auto</ChoiceHistoryOnInput>
					<DenyIncompleteValues>false</DenyIncompleteValues>
					<BaseDimension>false</BaseDimension>
					<ScheduleLink/>
					<Indexing>DontIndex</Indexing>
					<FullTextSearch>Use</FullTextSearch>
				</Properties>
			</Dimension>
			<Form>ФормаСписка</Form>
		</ChildObjects>
	</CalculationRegister>
</MetaDataObject>